MANIFEST.in
README.rst
fileidentify.py
setup.cfg
setup.py
fileidentify.egg-info/PKG-INFO
fileidentify.egg-info/SOURCES.txt
fileidentify.egg-info/dependency_links.txt
fileidentify.egg-info/entry_points.txt
fileidentify.egg-info/requires.txt
fileidentify.egg-info/top_level.txt